django_storages_redux-1.3.2.dist-info/DESCRIPTION.rst
django_storages_redux-1.3.2.dist-info/METADATA
django_storages_redux-1.3.2.dist-info/RECORD
django_storages_redux-1.3.2.dist-info/WHEEL
django_storages_redux-1.3.2.dist-info/metadata.json
django_storages_redux-1.3.2.dist-info/top_level.txt
storages/__init__.py
storages/compat.py
storages/utils.py
storages/backends/__init__.py
storages/backends/apache_libcloud.py
storages/backends/azure_storage.py
storages/backends/couchdb.py
storages/backends/database.py
storages/backends/dropbox.py
storages/backends/ftp.py
storages/backends/gs.py
storages/backends/hashpath.py
storages/backends/image.py
storages/backends/mogile.py
storages/backends/overwrite.py
storages/backends/s3boto.py
storages/backends/sftpstorage.py
storages/backends/symlinkorcopy.py
