Metadata-Version: 2.0
Name: django-storages-redux
Version: 1.3.2
Summary: Support for many storages (S3, MogileFS, etc) in Django.
Home-page: https://github.com/jschneier/django-storages
Author: Josh Schneier
Author-email: josh.schneier@gmail.com
License: BSD
Platform: UNKNOWN
Classifier: Framework :: Django
Classifier: Development Status :: 5 - Production/Stable
Classifier: Environment :: Web Environment
Classifier: Intended Audience :: Developers
Classifier: License :: OSI Approved :: BSD License
Classifier: Operating System :: OS Independent
Classifier: Programming Language :: Python
Classifier: Programming Language :: Python :: 2
Classifier: Programming Language :: Python :: 2.7
Classifier: Programming Language :: Python :: 3
Classifier: Programming Language :: Python :: 3.3
Classifier: Programming Language :: Python :: 3.4
